LICENSE.txt
README.md
setup.py
flopz/__init__.py
flopz.egg-info/PKG-INFO
flopz.egg-info/SOURCES.txt
flopz.egg-info/dependency_links.txt
flopz.egg-info/requires.txt
flopz.egg-info/top_level.txt
flopz/arch/__init__.py
flopz/arch/architecture.py
flopz/arch/auto_instruction.py
flopz/arch/exceptions.py
flopz/arch/instruction.py
flopz/arch/operands.py
flopz/arch/register.py
flopz/arch/arm/__init__.py
flopz/arch/arm/arm_generic_arch.py
flopz/arch/arm/thumb/__init__.py
flopz/arch/arm/thumb/auto_instructions.py
flopz/arch/arm/thumb/instructions.py
flopz/arch/arm/thumb/stm32F407.py
flopz/arch/ia32/__init__.py
flopz/arch/ia32/addressing.py
flopz/arch/ia32/auto_instructions.py
flopz/arch/ia32/conditionals.py
flopz/arch/ia32/ia32_generic_arch.py
flopz/arch/ia32/instruction_components.py
flopz/arch/ia32/instructions.py
flopz/arch/ia32/modes.py
flopz/arch/ppc/__init__.py
flopz/arch/ppc/ppc_generic_arch.py
flopz/arch/ppc/vle/__init__.py
flopz/arch/ppc/vle/auto_instructions.py
flopz/arch/ppc/vle/e200z0.py
flopz/arch/ppc/vle/instructions.py
flopz/arch/ppc/vle/registers.py
flopz/arch/ppc/vle/vle.py
flopz/arch/riscv/__init__.py
flopz/arch/riscv/registers.py
flopz/arch/riscv/riscv_generic_arch.py
flopz/arch/riscv/rv32c/__init__.py
flopz/arch/riscv/rv32c/instructions.py
flopz/arch/riscv/rv32i/__init__.py
flopz/arch/riscv/rv32i/instructions.py
flopz/arch/riscv/rv32i/rv32i_arch.py
flopz/core/__init__.py
flopz/core/addressable_object.py
flopz/core/assembler.py
flopz/core/function.py
flopz/core/label.py
flopz/core/module.py
flopz/core/shellcode.py
flopz/core/target.py
flopz/listener/__init__.py
flopz/listener/event.py
flopz/listener/flopz_logger.py
flopz/listener/link.py
flopz/listener/protocol.py
flopz/listener/events/__init__.py
flopz/listener/events/function_trace_event.py
flopz/listener/links/__init__.py
flopz/listener/links/all_links.py
flopz/listener/links/socketcan_link.py
flopz/listener/loggers/__init__.py
flopz/listener/loggers/all_loggers.py
flopz/listener/loggers/chrome_trace_logger.py
flopz/listener/loggers/console_logger.py
flopz/listener/loggers/json_file_logger.py
flopz/target/__init__.py
flopz/target/all_targets.py
